pynipkg/__init__.py
pynipkg/builder.py
pynipkg/example.py
pynipkg/main.py
pynipkg/pspec.py
pynipkg/run_commands_utility.py
pynipkg-0.1.0.dist-info/WHEEL
pynipkg-0.1.0.dist-info/entry_points.txt
pynipkg-0.1.0.dist-info/METADATA
pynipkg-0.1.0.dist-info/RECORD
