Metadata-Version: 2.3
Name: pynipkg
Version: 0.1.0
Summary: Scripts for automating nipkg package building using the CLI
Author: Karthick Shanmuga Rao
Author-email: Karthick Shanmuga Rao <karthikssfeb@gmail.com>
License: MIT License
Requires-Python: >=3.10
